exponent_server_sdk/__init__.py
exponent_server_sdk-2.0.0.dist-info/LICENSE
exponent_server_sdk-2.0.0.dist-info/METADATA
exponent_server_sdk-2.0.0.dist-info/WHEEL
exponent_server_sdk-2.0.0.dist-info/top_level.txt
exponent_server_sdk-2.0.0.dist-info/RECORD
