Metadata-Version: 2.1
Name: exponent_server_sdk
Version: 2.0.0
Summary: Expo Server SDK for Python
Home-page: https://github.com/expo/exponent-server-sdk-python
Author: Expo Team
Author-email: exponent.team@gmail.com
License: MIT
Platform: UNKNOWN
